{
    "nodes": [
        {
            "id": "2280",
            "name": "Maria Arnelid",
            "link": "https://dl.acm.org/profile/99660650690"
        },
        {
            "id": "2278",
            "name": "Katie Winkle",
            "link": "https://dl.acm.org/profile/99659217102"
        },
        {
            "id": "2279",
            "name": "Donald McMillan",
            "link": "https://dl.acm.org/profile/81484646781"
        },
        {
            "id": "2281",
            "name": "Katherine Harrison",
            "link": "https://dl.acm.org/profile/81474683876"
        },
        {
            "id": "2283",
            "name": "Iolanda Leite",
            "link": "https://dl.acm.org/profile/81367599529"
        },
        {
            "id": "1572",
            "name": "Madeline Balaam",
            "link": "https://dl.acm.org/profile/81448600301"
        },
        {
            "id": "2282",
            "name": "Ericka Johnson",
            "link": "https://dl.acm.org/profile/99660753358"
        },
        {
            "id": "2438",
            "name": "Sofia Thunberg",
            "link": "https://dl.acm.org/profile/99659211928"
        },
        {
            "id": "2439",
            "name": "Tom Ziemke",
            "link": "https://dl.acm.org/profile/81100607269"
        }
    ],
    "links": [
        {
            "source": "2278",
            "target": "2279"
        },
        {
            "source": "2278",
            "target": "2281"
        },
        {
            "source": "2278",
            "target": "2283"
        },
        {
            "source": "2278",
            "target": "1572"
        },
        {
            "source": "2278",
            "target": "2282"
        },
        {
            "source": "2279",
            "target": "2281"
        },
        {
            "source": "2279",
            "target": "2283"
        },
        {
            "source": "2279",
            "target": "1572"
        },
        {
            "source": "2279",
            "target": "2282"
        },
        {
            "source": "2281",
            "target": "2283"
        },
        {
            "source": "2281",
            "target": "1572"
        },
        {
            "source": "2281",
            "target": "2282"
        },
        {
            "source": "2283",
            "target": "1572"
        },
        {
            "source": "2283",
            "target": "2282"
        },
        {
            "source": "1572",
            "target": "2282"
        },
        {
            "source": "2438",
            "target": "2439"
        },
        {
            "source": "2280",
            "target": "2278"
        },
        {
            "source": "2280",
            "target": "2279"
        },
        {
            "source": "2280",
            "target": "2281"
        },
        {
            "source": "2280",
            "target": "2283"
        },
        {
            "source": "2280",
            "target": "1572"
        },
        {
            "source": "2280",
            "target": "2282"
        },
        {
            "source": "2280",
            "target": "2438"
        },
        {
            "source": "2280",
            "target": "2439"
        },
        {
            "source": "2280",
            "target": "2438"
        }
    ]
}